{
    "black_list": [
      {
        "s": "FWB:02M",
        "f": [
          "empty symbol"
        ]
      },
      {
        "s": "FWB:0U6",
        "f": [
          "empty symbol"
        ]
      },
      {
        "s": "FWB:1CT",
        "f": [
          "empty symbol"
        ]
      },
      {
        "s": "FWB:1NR",
        "f": [
          "empty symbol"
        ]
      },
      {
        "s": "FWB:4PN",
        "f": [
          "empty symbol"
        ]
      },
      {
        "s": "FWB:4UBP",
        "f": [
          "empty symbol"
        ]
      },
      {
        "s": "FWB:ADS",
        "f": [
          "empty symbol"
        ]
      },
      {
        "s": "FWB:BNRN",
        "f": [
          "no longer trading"
        ]
      },
      {
        "s": "FWB:BRZ",
        "f": [
          "empty symbol"
        ]
      },
      {
        "s": "FWB:BSP",
        "f": [
          "empty symbol"
        ]
      },
      {
        "s": "FWB:BYW",
        "f": [
          "empty symbol"
        ]
      },
      {
        "s": "FWB:BYW6",
        "f": [
          "empty symbol"
        ]
      },
      {
        "s": "FWB:C53",
        "f": [
          "empty symbol"
        ]
      },
      {
        "s": "FWB:C9N",
        "f": [
          "empty symbol"
        ]
      },
      {
        "s": "FWB:CAT1",
        "f": [
          "empty symbol"
        ]
      },
      {
        "s": "FWB:CB4",
        "f": [
          "empty symbol"
        ]
      },
      {
        "s": "FWB:COP",
        "f": [
          "empty symbol"
        ]
      },
      {
        "s": "FWB:CVS",
        "f": [
          "empty symbol"
        ]
      },
      {
        "s": "FWB:DCV",
        "f": [
          "empty symbol"
        ]
      },
      {
        "s": "FWB:DP4B",
        "f": [
          "empty symbol"
        ]
      },
      {
        "s": "FWB:EFF",
        "f": [
          "empty symbol"
        ]
      },
      {
        "s": "FWB:ETG",
        "f": [
          "empty symbol"
        ]
      },
      {
        "s": "FWB:EVT",
        "f": [
          "empty symbol"
        ]
      },
      {
        "s": "FWB:EVTA",
        "f": [
          "empty symbol"
        ]
      },
      {
        "s": "FWB:FTK",
        "f": [
          "empty symbol"
        ]
      },
      {
        "s": "FWB:G02",
        "f": [
          "empty symbol"
        ]
      },
      {
        "s": "FWB:IC8",
        "f": [
          "empty symbol"
        ]
      },
      {
        "s": "FWB:ILMJ",
        "f": [
          "empty symbol"
        ]
      },
      {
        "s": "FWB:JEN",
        "f": [
          "empty symbol"
        ]
      },
      {
        "s": "FWB:KRN",
        "f": [
          "empty symbol"
        ]
      },
      {
        "s": "FWB:LHL1",
        "f": [
          "empty symbol"
        ]
      },
      {
        "s": "FWB:MG9",
        "f": [
          "empty symbol"
        ]
      },
      {
        "s": "FWB:MHL",
        "f": [
          "empty symbol"
        ]
      },
      {
        "s": "FWB:MLB1",
        "f": [
          "empty symbol"
        ]
      },
      {
        "s": "FWB:MUV2",
        "f": [
          "empty symbol"
        ]
      },
      {
        "s": "FWB:N2F",
        "f": [
          "empty symbol"
        ]
      },
      {
        "s": "FWB:NGDA",
        "f": [
          "empty symbol"
        ]
      },
      {
        "s": "FWB:OCZA",
        "f": [
          "empty symbol"
        ]
      },
      {
        "s": "FWB:PGV",
        "f": [
          "empty symbol"
        ]
      },
      {
        "s": "FWB:PIR",
        "f": [
          "empty symbol"
        ]
      },
      {
        "s": "FWB:PWC",
        "f": [
          "empty symbol"
        ]
      },
      {
        "s": "FWB:QCI",
        "f": [
          "empty symbol"
        ]
      },
      {
        "s": "FWB:QJE",
        "f": [
          "empty symbol"
        ]
      },
      {
        "s": "FWB:RI7",
        "f": [
          "empty symbol"
        ]
      },
      {
        "s": "FWB:S1R",
        "f": [
          "empty symbol"
        ]
      },
      {
        "s": "FWB:SBNC",
        "f": [
          "empty symbol"
        ]
      },
      {
        "s": "FWB:SCT",
        "f": [
          "empty symbol"
        ]
      },
      {
        "s": "FWB:SD1",
        "f": [
          "empty symbol"
        ]
      },
      {
        "s": "FWB:SMS2",
        "f": [
          "empty symbol"
        ]
      },
      {
        "s": "FWB:SPM",
        "f": [
          "empty symbol"
        ]
      },
      {
        "s": "FWB:TCID",
        "f": [
          "empty symbol"
        ]
      },
      {
        "s": "FWB:TO6",
        "f": [
          "empty symbol"
        ]
      },
      {
        "s": "FWB:TTO",
        "f": [
          "empty symbol"
        ]
      },
      {
        "s": "FWB:U9RA",
        "f": [
          "empty symbol"
        ]
      },
      {
        "s": "FWB:UBK",
        "f": [
          "empty symbol"
        ]
      },
      {
        "s": "FWB:V6C",
        "f": [
          "empty symbol"
        ]
      },
      {
        "s": "FWB:WSU",
        "f": [
          "empty symbol"
        ]
      },
      {
        "s": "FWB:ZYA",
        "f": [
          "empty symbol"
        ]
      },
      {
        "s": "SWB:1Q7",
        "f": [
          "no longer trading"
        ]
      },
      {
        "s": "SWB:3BG",
        "f": [
          "no longer trading"
        ]
      },
      {
        "s": "SWB:4J6",
        "f": [
          "no longer trading"
        ]
      },
      {
        "s": "SWB:ABEA",
        "f": [
          "empty symbol"
        ]
      },
      {
        "s": "SWB:ABEC",
        "f": [
          "empty symbol"
        ]
      },
      {
        "s": "SWB:AGJ",
        "f": [
          "empty symbol"
        ]
      },
      {
        "s": "SWB:AGR",
        "f": [
          "equal bars"
        ]
      },
      {
        "s": "SWB:ANGA",
        "f": [
          "no longer trading"
        ]
      },
      {
        "s": "SWB:B5H",
        "f": [
          "no longer trading"
        ]
      },
      {
        "s": "SWB:BAS",
        "f": [
          "empty symbol"
        ]
      },
      {
        "s": "SWB:BKMA",
        "f": [
          "no longer trading"
        ]
      },
      {
        "s": "SWB:BNP",
        "f": [
          "empty symbol"
        ]
      },
      {
        "s": "SWB:C4C",
        "f": [
          "empty symbol"
        ]
      },
      {
        "s": "SWB:CLRN",
        "f": [
          "no longer trading"
        ]
      },
      {
        "s": "SWB:CMS",
        "f": [
          "empty symbol"
        ]
      },
      {
        "s": "SWB:CP9",
        "f": [
          "empty symbol"
        ]
      },
      {
        "s": "SWB:CXU",
        "f": [
          "empty symbol"
        ]
      },
      {
        "s": "SWB:DPWA",
        "f": [
          "empty symbol"
        ]
      },
      {
        "s": "SWB:E9NB",
        "f": [
          "no longer trading"
        ]
      },
      {
        "s": "SWB:ED4",
        "f": [
          "no longer trading"
        ]
      },
      {
        "s": "SWB:EYP",
        "f": [
          "empty symbol"
        ]
      },
      {
        "s": "SWB:G1A",
        "f": [
          "empty symbol"
        ]
      },
      {
        "s": "SWB:GEY",
        "f": [
          "no longer trading"
        ]
      },
      {
        "s": "SWB:H9W",
        "f": [
          "empty symbol"
        ]
      },
      {
        "s": "SWB:HAS",
        "f": [
          "empty symbol"
        ]
      },
      {
        "s": "SWB:HHFA",
        "f": [
          "empty symbol"
        ]
      },
      {
        "s": "SWB:HLG",
        "f": [
          "no longer trading"
        ]
      },
      {
        "s": "SWB:I43",
        "f": [
          "empty symbol"
        ]
      },
      {
        "s": "SWB:L60",
        "f": [
          "empty symbol"
        ]
      },
      {
        "s": "SWB:LOR",
        "f": [
          "empty symbol"
        ]
      },
      {
        "s": "SWB:MDBA",
        "f": [
          "empty symbol"
        ]
      },
      {
        "s": "SWB:MYRK",
        "f": [
          "empty symbol"
        ]
      },
      {
        "s": "SWB:N7G",
        "f": [
          "empty symbol"
        ]
      },
      {
        "s": "SWB:NESR",
        "f": [
          "no longer trading"
        ]
      },
      {
        "s": "SWB:NGLB",
        "f": [
          "empty symbol"
        ]
      },
      {
        "s": "SWB:OWX",
        "f": [
          "no longer trading"
        ]
      },
      {
        "s": "SWB:PJZ",
        "f": [
          "empty symbol"
        ]
      },
      {
        "s": "SWB:PRRB",
        "f": [
          "empty symbol"
        ]
      },
      {
        "s": "SWB:RITN",
        "f": [
          "no longer trading"
        ]
      },
      {
        "s": "SWB:RKET",
        "f": [
          "empty symbol"
        ]
      },
      {
        "s": "SWB:RPL",
        "f": [
          "empty symbol"
        ]
      },
      {
        "s": "SWB:SFD1",
        "f": [
          "empty symbol"
        ]
      },
      {
        "s": "SWB:SFE",
        "f": [
          "empty symbol"
        ]
      },
      {
        "s": "SWB:SGR",
        "f": [
          "empty symbol"
        ]
      },
      {
        "s": "SWB:SHD",
        "f": [
          "empty symbol"
        ]
      },
      {
        "s": "SWB:SIX2",
        "f": [
          "empty symbol"
        ]
      },
      {
        "s": "SWB:SLW",
        "f": [
          "no longer trading"
        ]
      },
      {
        "s": "SWB:SQL",
        "f": [
          "no longer trading"
        ]
      },
      {
        "s": "SWB:SR9",
        "f": [
          "no longer trading"
        ]
      },
      {
        "s": "SWB:TSFA",
        "f": [
          "empty symbol"
        ]
      },
      {
        "s": "SWB:VRS",
        "f": [
          "empty symbol"
        ]
      },
      {
        "s": "SWB:WIG1",
        "f": [
          "empty symbol"
        ]
      },
      {
        "s": "XETR:02M",
        "f": [
          "empty symbol"
        ]
      },
      {
        "s": "XETR:0PP",
        "f": [
          "empty symbol"
        ]
      },
      {
        "s": "XETR:1Q7",
        "f": [
          "no longer trading"
        ]
      },
      {
        "s": "XETR:4JMA",
        "f": [
          "empty symbol"
        ]
      },
      {
        "s": "XETR:4UBP",
        "f": [
          "empty symbol"
        ]
      },
      {
        "s": "XETR:5FB",
        "f": [
          "empty symbol"
        ]
      },
      {
        "s": "XETR:6MK",
        "f": [
          "empty symbol"
        ]
      },
      {
        "s": "XETR:A1A4FR",
        "f": [
          "empty symbol"
        ]
      },
      {
        "s": "XETR:A254W1",
        "f": [
          "empty symbol"
        ]
      },
      {
        "s": "XETR:A289AV",
        "f": [
          "empty symbol"
        ]
      },
      {
        "s": "XETR:ADL2",
        "f": [
          "empty symbol"
        ]
      },
      {
        "s": "XETR:AFX",
        "f": [
          "empty symbol"
        ]
      },
      {
        "s": "XETR:AMG",
        "f": [
          "empty symbol"
        ]
      },
      {
        "s": "XETR:ANGA",
        "f": [
          "no longer trading"
        ]
      },
      {
        "s": "XETR:ANL",
        "f": [
          "empty symbol"
        ]
      },
      {
        "s": "XETR:AWM",
        "f": [
          "empty symbol"
        ]
      },
      {
        "s": "XETR:BAC",
        "f": [
          "empty symbol"
        ]
      },
      {
        "s": "XETR:BNRA",
        "f": [
          "empty symbol"
        ]
      },
      {
        "s": "XETR:BNRN",
        "f": [
          "empty symbol"
        ]
      },
      {
        "s": "XETR:BTBB",
        "f": [
          "empty symbol"
        ]
      },
      {
        "s": "XETR:DAM",
        "f": [
          "empty symbol"
        ]
      },
      {
        "s": "XETR:FREN",
        "f": [
          "no longer trading"
        ]
      },
      {
        "s": "XETR:GIL",
        "f": [
          "empty symbol"
        ]
      },
      {
        "s": "XETR:GOB",
        "f": [
          "empty symbol"
        ]
      },
      {
        "s": "XETR:GTY",
        "f": [
          "empty symbol"
        ]
      },
      {
        "s": "XETR:HCL",
        "f": [
          "empty symbol"
        ]
      },
      {
        "s": "XETR:ILMJ",
        "f": [
          "empty symbol"
        ]
      },
      {
        "s": "XETR:IXD1",
        "f": [
          "empty symbol"
        ]
      },
      {
        "s": "XETR:L60",
        "f": [
          "no longer trading"
        ]
      },
      {
        "s": "XETR:LEGU",
        "f": [
          "empty symbol"
        ]
      },
      {
        "s": "XETR:M3V",
        "f": [
          "empty symbol"
        ]
      },
      {
        "s": "XETR:MGNK",
        "f": [
          "empty symbol"
        ]
      },
      {
        "s": "XETR:MPCK",
        "f": [
          "empty symbol"
        ]
      },
      {
        "s": "XETR:MTXC",
        "f": [
          "empty symbol"
        ]
      },
      {
        "s": "XETR:MXI",
        "f": [
          "empty symbol"
        ]
      },
      {
        "s": "XETR:MZP",
        "f": [
          "no longer trading"
        ]
      },
      {
        "s": "XETR:NESR",
        "f": [
          "no longer trading"
        ]
      },
      {
        "s": "XETR:NGLD",
        "f": [
          "no longer trading"
        ]
      },
      {
        "s": "XETR:NOEJ",
        "f": [
          "empty symbol"
        ]
      },
      {
        "s": "XETR:NWT",
        "f": [
          "empty symbol"
        ]
      },
      {
        "s": "XETR:PPX",
        "f": [
          "empty symbol"
        ]
      },
      {
        "s": "XETR:RNL1",
        "f": [
          "no longer trading"
        ]
      },
      {
        "s": "XETR:SDF1",
        "f": [
          "no longer trading"
        ]
      },
      {
        "s": "XETR:SNH",
        "f": [
          "empty symbol"
        ]
      },
      {
        "s": "XETR:SQL",
        "f": [
          "no longer trading"
        ]
      },
      {
        "s": "XETR:SR9",
        "f": [
          "no longer trading"
        ]
      },
      {
        "s": "XETR:TGR",
        "f": [
          "empty symbol"
        ]
      },
      {
        "s": "XETR:TUF",
        "f": [
          "empty symbol"
        ]
      },
      {
        "s": "XETR:US399473107",
        "f": [
          "no longer trading"
        ]
      },
      {
        "s": "XETR:US399473206",
        "f": [
          "empty symbol"
        ]
      },
      {
        "s": "XETR:US52490H100",
        "f": [
          "empty symbol"
        ]
      },
      {
        "s": "XETR:US72352L106",
        "f": [
          "empty symbol"
        ]
      },
      {
        "s": "XETR:WAC",
        "f": [
          "empty symbol"
        ]
      },
      {
        "s": "XETR:YSN",
        "f": [
          "empty symbol"
        ]
      },
      {
        "s": "XETR:ZSOL",
        "f": [
          "empty symbol"
        ]
      }
    ]
  }